Metadata-Version: 2.1
Name: odoo-addon-delivery_dropoff_site
Version: 18.0.1.0.0.11
Requires-Python: >=3.10
Requires-Dist: odoo==18.0.*
Summary: Send goods to sites in which customers come pick up package
Home-page: https://github.com/OCA/delivery-carrier
License: AGPL-3
Author: Akretion,GRAP,Odoo Community Association (OCA)
Author-email: support@odoo-community.org
Classifier: Programming Language :: Python
Classifier: Framework :: Odoo
Classifier: Framework :: Odoo :: 18.0
Classifier: License :: OSI Approved :: GNU Affero General Public License v3
